calcwave/__init__.py
calcwave/__main__.py
calcwave/calcwave.py
calcwave/dependencyWizard.py
calcwave/mathextensions.py
calcwave-1.6.2.dist-info/LICENSE.txt
calcwave-1.6.2.dist-info/METADATA
calcwave-1.6.2.dist-info/WHEEL
calcwave-1.6.2.dist-info/entry_points.txt
calcwave-1.6.2.dist-info/top_level.txt
calcwave-1.6.2.dist-info/RECORD
