Metadata-Version: 2.1
Name: calcwave
Version: 1.6.2
Summary: A simple cross-platform utility for generating and playing audio using a mathematical formula 
Home-page: https://github.com/zenarcher007/calcwave
Download-URL: https://github.com/zenarcher007/calcwave/archive/refs/tags/v1.6.0.tar.gz
Author: Justin Douty
License: gpl-3.0
Keywords: cross-platform,audio synthesis,terminal,user-friendly
Classifier: Development Status :: 4 - Beta
Classifier: Intended Audience :: End Users/Desktop
Classifier: Topic :: Multimedia :: Sound/Audio :: Sound Synthesis
Classifier: License :: OSI Approved :: GNU General Public License v3 (GPLv3)
Classifier: Programming Language :: Python :: 3
Classifier: Programming Language :: Python :: 3.6
Classifier: Programming Language :: Python :: 3.7
Classifier: Programming Language :: Python :: 3.8
Classifier: Programming Language :: Python :: 3.9
License-File: LICENSE.txt
Requires-Dist: numpy
Requires-Dist: argparse
Requires-Dist: windows-curses ; platform_system == "Windows"
